_version.py
command.py
how.py
how-0.1.1.dist-info/LICENSE
how-0.1.1.dist-info/METADATA
how-0.1.1.dist-info/WHEEL
how-0.1.1.dist-info/entry_points.txt
how-0.1.1.dist-info/top_level.txt
how-0.1.1.dist-info/RECORD
